LICENSE
README.md
pyproject.toml
examples/blend_and_shuffle.py
examples/classifier_filtering.py
examples/download_arxiv.py
examples/download_common_crawl.py
examples/download_wikipedia.py
examples/exact_deduplication.py
examples/find_pii_and_deidentify.py
examples/fineweb_edu_classifier_example.py
examples/fuzzy_deduplication.py
examples/identify_languages_and_fix_unicode.py
examples/raw_download_common_crawl.py
examples/semdedup_example.py
examples/task_decontamination.py
examples/translation_example.py
examples/classifiers/aegis_example.py
examples/classifiers/domain_example.py
examples/classifiers/fineweb_edu_example.py
examples/classifiers/quality_example.py
examples/k8s/create_dask_cluster.py
examples/nemo_run/launch_slurm.py
lava_ray.egg-info/PKG-INFO
lava_ray.egg-info/SOURCES.txt
lava_ray.egg-info/dependency_links.txt
lava_ray.egg-info/entry_points.txt
lava_ray.egg-info/requires.txt
lava_ray.egg-info/top_level.txt
nemo_curator/__init__.py
nemo_curator/_compat.py
nemo_curator/log.py
nemo_curator/sample_dataframe.py
nemo_curator/classifiers/__init__.py
nemo_curator/classifiers/aegis.py
nemo_curator/classifiers/base.py
nemo_curator/classifiers/domain.py
nemo_curator/classifiers/fineweb_edu.py
nemo_curator/classifiers/quality.py
nemo_curator/datasets/__init__.py
nemo_curator/datasets/doc_dataset.py
nemo_curator/datasets/image_text_pair_dataset.py
nemo_curator/datasets/nsys_script.py
nemo_curator/download/__init__.py
nemo_curator/download/arxiv.py
nemo_curator/download/commoncrawl.py
nemo_curator/download/doc_builder.py
nemo_curator/download/thai_stopwords.py
nemo_curator/download/wikipedia.py
nemo_curator/filters/__init__.py
nemo_curator/filters/classifier_filter.py
nemo_curator/filters/code.py
nemo_curator/filters/doc_filter.py
nemo_curator/filters/heuristic_filter.py
nemo_curator/image/__init__.py
nemo_curator/image/classifiers/__init__.py
nemo_curator/image/classifiers/aesthetic.py
nemo_curator/image/classifiers/base.py
nemo_curator/image/classifiers/nsfw.py
nemo_curator/image/embedders/__init__.py
nemo_curator/image/embedders/base.py
nemo_curator/image/embedders/timm.py
nemo_curator/modifiers/__init__.py
nemo_curator/modifiers/c4.py
