Metadata-Version: 2.1
Name: lava_ray
Version: 0.6.0.dev0
Summary: Scalable Data Preprocessing Tool for Training Large Language Models
Author-email: Joseph Jennings <jjennings@nvidia.com>, Mostofa Patwary <mpatwary@nvidia.com>, Sandeep Subramanian <sasubramania@nvidia.com>, Shrimai Prabhumoye <sprabhumoye@nvidia.com>, Ayush Dattagupta <adattagupta@nvidia.com>, Vibhu Jawa <vjawa@nvidia.com>, Jiwei Liu <jiweil@nvidia.com>, Ryan Wolf <rywolf@nvidia.com>, Sarah Yurick <syurick@nvidia.com>
Project-URL: Homepage, https://github.com/NVIDIA/NeMo-Curator
Classifier: Development Status :: 3 - Alpha
Classifier: Programming Language :: Python :: 3
Classifier: Programming Language :: Python :: 3.10
Requires-Python: <3.11,>=3.10
License-File: LICENSE
Requires-Dist: awscli>=1.22.55
Requires-Dist: beautifulsoup4
Requires-Dist: charset_normalizer>=3.1.0
Requires-Dist: comment_parser
Requires-Dist: crossfit>=0.0.6
Requires-Dist: dask-mpi>=2021.11.0
Requires-Dist: dask[complete]>=2021.7.1
Requires-Dist: distributed>=2021.7.1
Requires-Dist: fasttext==0.9.2
Requires-Dist: ftfy==6.1.1
Requires-Dist: in-place==0.5.0
Requires-Dist: jieba==0.42.1
Requires-Dist: justext==3.0.1
Requires-Dist: lxml_html_clean
Requires-Dist: mecab-python3
Requires-Dist: mwparserfromhell==0.6.5
Requires-Dist: nemo_toolkit[nlp]>=1.23.0
Requires-Dist: numpy<2
Requires-Dist: openai
Requires-Dist: peft
Requires-Dist: presidio-analyzer==2.2.351
Requires-Dist: presidio-anonymizer==2.2.351
Requires-Dist: pycld2
Requires-Dist: resiliparse
Requires-Dist: spacy<3.8.0,>=3.6.0
Requires-Dist: unidic-lite==1.0.8
Requires-Dist: usaddress==0.5.10
Requires-Dist: warcio==1.7.4
Requires-Dist: zstandard==0.18.0
Provides-Extra: cuda12x
Requires-Dist: cudf-cu12>=24.10; extra == "cuda12x"
Requires-Dist: cugraph-cu12>=24.10; extra == "cuda12x"
Requires-Dist: cuml-cu12>=24.10; extra == "cuda12x"
Requires-Dist: dask-cuda>=24.10; extra == "cuda12x"
Requires-Dist: dask-cudf-cu12>=24.10; extra == "cuda12x"
Requires-Dist: spacy[cuda12x]<3.8.0,>=3.6.0; extra == "cuda12x"
Provides-Extra: cuda12x-nightly
Requires-Dist: cudf-cu12<=24.12,>=24.12.0a0; extra == "cuda12x-nightly"
Requires-Dist: cugraph-cu12<=24.12,>=24.12.0a0; extra == "cuda12x-nightly"
Requires-Dist: cuml-cu12<=24.12,>=24.12.0a0; extra == "cuda12x-nightly"
Requires-Dist: dask-cuda<=24.12,>=24.12.0a0; extra == "cuda12x-nightly"
Requires-Dist: dask-cudf-cu12<=24.12,>=24.12.0a0; extra == "cuda12x-nightly"
Requires-Dist: spacy[cuda12x]<3.8.0,>=3.6.0; extra == "cuda12x-nightly"
Provides-Extra: image
Requires-Dist: nvidia-dali-cuda120; extra == "image"
Requires-Dist: nvidia-nvjpeg2k-cu12; extra == "image"
Requires-Dist: timm>=1.0.8; extra == "image"
Requires-Dist: lava_ray[cuda12x]; extra == "image"
Provides-Extra: image-nightly
Requires-Dist: nvidia-dali-cuda120; extra == "image-nightly"
Requires-Dist: nvidia-nvjpeg2k-cu12; extra == "image-nightly"
Requires-Dist: timm>=1.0.8; extra == "image-nightly"
Requires-Dist: lava_ray[cuda12x_nightly]; extra == "image-nightly"
Provides-Extra: all
Requires-Dist: lava_ray[image]; extra == "all"
Provides-Extra: all-nightly
Requires-Dist: lava_ray[image_nightly]; extra == "all-nightly"
